{
    "employees":
    [
        {"name": "Nash", "age": 37, "gender": "female"},
        {"name": "Divine", "age": 5, "gender": "male"},
        {"name": "Eva", "age": 39, "gender": "female"},
        {"name": "Josh", "age": 10, "gender": "male"},
        {
            "name": "Comfort", 
            "age": 40, 
            "gender": "female",
            "address": [
                {"type": "Office", "street":""},
                {"type": "Home", "street": ""}
            ]
        }
            
    ]
    
}